cardio/__init__.py
cardio/app.py
cardio/assets/bone.toml
cardio/assets/vascular_closed.toml
cardio/assets/vascular_open.toml
cardio/assets/xray.toml
cardio/blend_transfer_functions.py
cardio/color_transfer_function.py
cardio/logic.py
cardio/mesh.py
cardio/object.py
cardio/orientation.py
cardio/piecewise_function.py
cardio/property_config.py
cardio/rotation.py
cardio/scene.py
cardio/screenshot.py
cardio/segmentation.py
cardio/transfer_function_pair.py
cardio/types.py
cardio/ui.py
cardio/utils.py
cardio/volume.py
cardio/volume_property.py
cardio/volume_property_presets.py
cardio/window_level.py
cardio-2026.2.0.dist-info/WHEEL
cardio-2026.2.0.dist-info/entry_points.txt
cardio-2026.2.0.dist-info/METADATA
cardio-2026.2.0.dist-info/RECORD
