Metadata-Version: 2.3
Name: cardio
Version: 2026.2.0
Summary: A simple web-based viewer for 3D and 4D ('cine') medical imaging data.
Keywords: Medical,Imaging,3D,4D,Visualization
Author: Davis Marc Vigneault
Author-email: Davis Marc Vigneault <davis.vigneault@gmail.com>
License: Apache Software License 2.0
Classifier: Development Status :: 3 - Alpha
Classifier: Environment :: Web Environment
Classifier: Intended Audience :: Healthcare Industry
Classifier: Intended Audience :: Science/Research
Classifier: License :: OSI Approved :: Apache Software License
Classifier: Natural Language :: English
Classifier: Operating System :: OS Independent
Classifier: Programming Language :: Python :: 3 :: Only
Classifier: Programming Language :: JavaScript
Classifier: Topic :: Scientific/Engineering :: Image Processing
Classifier: Topic :: Scientific/Engineering :: Medical Science Apps.
Classifier: Topic :: Scientific/Engineering :: Visualization
Requires-Dist: trame-vuetify>=3.0.2
Requires-Dist: trame-vtk>=2.9.1
Requires-Dist: itk>=5.4.4.post1
Requires-Dist: vtk>=9.5.0
Requires-Dist: tomlkit>=0.13.3
Requires-Dist: numpy>=2.2.6
Requires-Dist: pydantic>=2.11.7
Requires-Dist: pydantic-settings>=2.0.0
Requires-Dist: trame>=3.12.0
Requires-Dist: trame-client>=3.10.1
Requires-Dist: ruff>=0.12.10 ; extra == 'dev'
Requires-Dist: isort>=6.0.1 ; extra == 'dev'
Requires-Dist: bumpver>=2025.1131 ; extra == 'dev'
Requires-Dist: pytest>=8.4.1 ; extra == 'dev'
Requires-Dist: coverage>=7.10.4 ; extra == 'dev'
Maintainer: Davis Marc Vigneault
Maintainer-email: Davis Marc Vigneault <davis.vigneault@gmail.com>
Requires-Python: >=3.10
Project-URL: repository, https://github.com/sudomakeinstall/cardio
Provides-Extra: dev
